MANIFEST.in
README.txt
setup.py
BazicCalculator.egg-info/PKG-INFO
BazicCalculator.egg-info/SOURCES.txt
BazicCalculator.egg-info/dependency_links.txt
BazicCalculator.egg-info/top_level.txt
CalculatorModules/__init__.py