Metadata-Version: 1.1
Name: BazicCalculator
Version: 0.0.1
Summary: A basic calculator that will be advancing every month or so
Home-page: UNKNOWN
Author: Mohammad Rahman
Author-email: mohammadnyc96@gmail.com
License: MIT
Platform: UNKNOWN
Classifier: Development Status :: 5 - Production/Stable
Classifier: Intended Audience :: Education
Classifier: Operating System :: Microsoft :: Windows :: Windows 10
Classifier: License :: OSI Approved :: MIT License
Classifier: Programming Language :: Python :: 3
